SimpleHTTPServe/__init__.py
SimpleHTTPServe/app.py
SimpleHTTPServe/response.py
SimpleHTTPServe/server.py
SimpleHTTPServe-0.0.3.dist-info/LICENSE
SimpleHTTPServe-0.0.3.dist-info/METADATA
SimpleHTTPServe-0.0.3.dist-info/WHEEL
SimpleHTTPServe-0.0.3.dist-info/top_level.txt
SimpleHTTPServe-0.0.3.dist-info/RECORD
